LICENSE.3RDPARTY
MANIFEST.in
README.md
SECURITY.md
requirements.txt
setup.py
django_tenants_manager.egg-info/PKG-INFO
django_tenants_manager.egg-info/SOURCES.txt
django_tenants_manager.egg-info/dependency_links.txt
django_tenants_manager.egg-info/not-zip-safe
django_tenants_manager.egg-info/requires.txt
django_tenants_manager.egg-info/top_level.txt
multitenancy/__init__.py
multitenancy/settings.py
multitenancy/urls.py
multitenancy/utils.py
multitenancy/admin/__init__.py
multitenancy/admin/admin.py
multitenancy/admin/apps.py
multitenancy/admin/customer_urls.py
multitenancy/admin/decorators.py
multitenancy/admin/events.py
multitenancy/admin/filters.py
multitenancy/admin/forms.py
multitenancy/admin/models.py
multitenancy/admin/team_urls.py
multitenancy/admin/urls.py
multitenancy/admin/migrations/__init__.py
multitenancy/admin/tests/__init__.py
multitenancy/admin/tests/test_views.py
multitenancy/admin/views/__init__.py
multitenancy/admin/views/adminViews.py
multitenancy/admin/views/authViews.py
multitenancy/admin/views/baseViews.py
multitenancy/admin/views/customerViews.py
multitenancy/admin/views/teamViews.py
multitenancy/apps/__init__.py
multitenancy/apps/admin.py
multitenancy/apps/apps.py
multitenancy/apps/models.py
multitenancy/apps/views.py
multitenancy/apps/migrations/0001_initial.py
multitenancy/apps/migrations/0002_initial.py
multitenancy/apps/migrations/0003_auto_20221111_1809.py
multitenancy/apps/migrations/0004_rename_packages_package.py
multitenancy/apps/migrations/0005_alter_tenanttype_name.py
multitenancy/apps/migrations/0006_alter_tenant_type.py
multitenancy/apps/migrations/0007_tenant_subscription.py
multitenancy/apps/migrations/0008_auto_20221208_1033.py
multitenancy/apps/migrations/0009_domain_has_custom.py
multitenancy/apps/migrations/0010_auto_20221210_1524.py
multitenancy/apps/migrations/__init__.py
multitenancy/core/EmailBackEnd.py
multitenancy/core/__init__.py
multitenancy/core/admin.py
multitenancy/core/apps.py
multitenancy/core/hooks.py
multitenancy/core/models.py
multitenancy/core/views.py
multitenancy/core/migrations/__init__.py
multitenancy/group/__init__.py
multitenancy/group/admin.py
multitenancy/group/apps.py
multitenancy/group/models.py
multitenancy/group/tests.py
multitenancy/group/views.py
