Metadata-Version: 1.2
Name: django-tenants-manager
Version: 0.0.1
Summary: A client portal in django for managing multi tenant saas apps for django tenants
Home-page: https://github.com/tekanokhambane/django-multitenancy
Author: Tekano Khambane
Author-email: tkhambane@gmail.com
Maintainer: Tekano Khambane
Maintainer-email: tkhambane@gmail.com
License: BSD
Keywords: django,django-tenats,multitenancy,django-multitenancy,multitenants,django-tenant-users,saas,django-saas,track,support
Platform: UNKNOWN
Classifier: Development Status :: 4 - Beta
Classifier: Programming Language :: Python
Classifier: Programming Language :: Python :: 3
Classifier: Programming Language :: Python :: 3.8
Classifier: Programming Language :: Python :: 3.9
Classifier: Programming Language :: Python :: 3.10
Classifier: Framework :: Django
Classifier: Framework :: Django :: 3.2
Classifier: Framework :: Django :: 4.0
Classifier: Environment :: Web Environment
Classifier: Operating System :: OS Independent
Classifier: Intended Audience :: Customer Service
Classifier: License :: OSI Approved :: BSD License
Classifier: Topic :: Software Development :: Bug Tracking
Classifier: Topic :: Software Development :: Libraries :: Python Modules
Classifier: Topic :: Office/Business
Classifier: Natural Language :: English
